{
  "title": "PF2e Vaulted Weapon Masters",
  "id": "pf2e-vaulted-weapon-masters",
  "description": "",
  "authors": [
    {
      "name": "Braden 'Delioth' Menke"
    },
    {
      "name":"Marceline Miller"
    },
    {
      "name": "Matthew 'comatthew6' Fu"
    },
    {
      "name": "Dylan Wojeck"
    }
  ],
  "manifest": "https://raw.githubusercontent.com/Eldritch-Osiris-Games/foundry-pf2e-vaulted-weapon-masters/main/module.json",
  "download": "https://github.com/Eldritch-Osiris-Games/foundry-pf2e-vaulted-weapon-masters/archive/refs/heads/main.zip",
  "url": "https://github.com/Eldritch-Osiris-Games/foundry-pf2e-vaulted-weapon-masters",
  "version": "0.9.2",
  "compatibility": {
    "minimum": "10",
    "verified": "10"
  },
  "esmodules": [
    "popup.js"
  ],
  "flags": {
    "pf2e-vaulted-weapon-masters": {
      "pf2e-homebrew": {
        "baseWeapons": {
          "reinforced-fishing-rod": "Reinforced Fishing Rod"
        },
        "featTraits": {
          "exertion": {
            "label": "Exertion",
            "description": "Actions with this trait tire you for their dramatic effects. Once you use an action with the exertion trait, you must rest for 10 minutes before using another exertion action. If you are not fatigued, you can use an exertion action when you need to rest, but doing so causes you to become fatigued until you rest for 10 minutes. Some feats or actions may have an additional effect designated as “Exert”; this means you can gain those described benefits by adding the exertion trait to the action."
          }
        }
      }
    }
  },
  "packs": [
    {
      "label": "Vaulted Weapon Masters Items",
      "type": "Item",
      "name": "vaulted-weapon-masters-items",
      "path": "./packs/vaulted-weapon-masters-items.db",
      "system": "pf2e"
    },
    {
      "label": "Vaulted Weapon Masters Feats",
      "type": "Item",
      "name": "vaulted-weapon-masters-feats",
      "path": "./packs/vaulted-weapon-masters-feats.db",
      "system": "pf2e"
    },
    {
      "label": "Vaulted Weapon Masters Effects & Actions",
      "type": "Item",
      "name": "vaulted-weapon-masters-effects-actions",
      "path": "./packs/vaulted-weapon-masters-effects-actions.db",
      "system": "pf2e"
    },
    {
      "label": "Vaulted Weapon Masters Journals",
      "type": "JournalEntry",
      "name": "vaulted-weapon-masters-journals",
      "path": "./packs/vaulted-weapon-masters-journals.db",
      "system": "pf2e"
    }
  ],
  "relationships": {
    "systems": {
        "id": "pf2e",
        "compatibility": {
          "minimum": "4.7.0"
        }
      }
  }
}
